openhab/__init__.py
openhab/item.py
openhab/__pycache__/__init__.cpython-38.pyc
openhab/__pycache__/item.cpython-38.pyc
python_openhab_item-1.0.0.dist-info/LICENSE
python_openhab_item-1.0.0.dist-info/METADATA
python_openhab_item-1.0.0.dist-info/WHEEL
python_openhab_item-1.0.0.dist-info/top_level.txt
python_openhab_item-1.0.0.dist-info/RECORD
