Metadata-Version: 2.1
Name: python-openhab-item
Version: 1.0.0
Summary: A simple class to represent items from openHAB. There is a separate object for each item type. The class can be used in conjunction with the REST API of openHAB.
Home-page: https://github.com/Michdo93/python-openhab-item
Download-URL: https://github.com/Michdo93/python-openhab-item
Author: Michael Dörflinger
Author-email: michaeldoerflinger93@gmail.com
License: MIT License
Project-URL: Bug Tracker, https://github.com/Michdo93/python-openhab-item/issues
Project-URL: Documentation, https://github.com/Michdo93/python-openhab-item/blob/main/README.md
Project-URL: Source Code, https://github.com/Michdo93/python-openhab-item
Keywords: openHAB
Classifier: Development Status :: 4 - Beta
Classifier: License :: OSI Approved :: MIT License
Classifier: Intended Audience :: Developers
Classifier: Operating System :: OS Independent
Classifier: Programming Language :: Python :: 3
Classifier: Programming Language :: Python :: 3 :: Only
Requires-Python: >=3.5
License-File: LICENSE
Requires-Dist: imageio (>=2.22.0)
Requires-Dist: opencv-python (>=4.6.0)
Requires-Dist: numpy (>=1.23.2)
